pyscancf/.DS_Store
pyscancf/__init__.py
pyscancf/cmapmaker.py
pyscancf/maxcappi.py
pyscancf/pyscancf.py
pyscancf/utils.py
pyscancf/version.py
pyscancf/__pycache__/__init__.cpython-39.pyc
pyscancf/__pycache__/pyscancf.cpython-39.pyc
pyscancf-2.0.4.dist-info/METADATA
pyscancf-2.0.4.dist-info/WHEEL
pyscancf-2.0.4.dist-info/top_level.txt
pyscancf-2.0.4.dist-info/RECORD
